{
    "dataset_name": "Dataset113_CTMulSegWholeData",
    "plans_name": "nnUNetPlans",
    "original_median_spacing_after_transp": [
        0.6000054478645325,
        0.3525390625,
        0.3525390625
    ],
    "original_median_shape_after_transp": [
        54,
        128,
        170
    ],
    "image_reader_writer": "SimpleITKIO",
    "transpose_forward": [
        0,
        1,
        2
    ],
    "transpose_backward": [
        0,
        1,
        2
    ],
    "configurations": {
        "2d": {
            "data_identifier": "nnUNetPlans_2d",
            "preprocessor_name": "DefaultPreprocessor",
            "batch_size": 102,
            "patch_size": [
                160,
                192
            ],
            "median_image_size_in_voxels": [
                131.0,
                174.0
            ],
            "spacing": [
                0.3525390625,
                0.3525390625
            ],
            "normalization_schemes": [
                "CTNormalization"
            ],
            "use_mask_for_norm": [
                false
            ],
            "UNet_class_name": "PlainConvUNet",
            "UNet_base_num_features": 32,
            "n_conv_per_stage_encoder": [
                2,
                2,
                2,
                2,
                2,
                2
            ],
            "n_conv_per_stage_decoder": [
                2,
                2,
                2,
                2,
                2
            ],
            "num_pool_per_axis": [
                5,
                5
            ],
            "pool_op_kernel_sizes": [
                [
                    1,
                    1
                ],
                [
                    2,
                    2
                ],
                [
                    2,
                    2
                ],
                [
                    2,
                    2
                ],
                [
                    2,
                    2
                ],
                [
                    2,
                    2
                ]
            ],
            "conv_kernel_sizes": [
                [
                    3,
                    3
                ],
                [
                    3,
                    3
                ],
                [
                    3,
                    3
                ],
                [
                    3,
                    3
                ],
                [
                    3,
                    3
                ],
                [
                    3,
                    3
                ]
            ],
            "unet_max_num_features": 512,
            "resampling_fn_data": "resample_data_or_seg_to_shape",
            "resampling_fn_seg": "resample_data_or_seg_to_shape",
            "resampling_fn_data_kwargs": {
                "is_seg": false,
                "order": 3,
                "order_z": 0,
                "force_separate_z": null
            },
            "resampling_fn_seg_kwargs": {
                "is_seg": true,
                "order": 1,
                "order_z": 0,
                "force_separate_z": null
            },
            "resampling_fn_probabilities": "resample_data_or_seg_to_shape",
            "resampling_fn_probabilities_kwargs": {
                "is_seg": false,
                "order": 1,
                "order_z": 0,
                "force_separate_z": null
            },
            "batch_dice": true
        },
        "3d_fullres": {
            "data_identifier": "nnUNetPlans_3d_fullres",
            "preprocessor_name": "DefaultPreprocessor",
            "batch_size": 3,
            "patch_size": [
                64,
                160,
                192
            ],
            "median_image_size_in_voxels": [
                57.0,
                131.0,
                174.0
            ],
            "spacing": [
                0.6000054478645325,
                0.3525390625,
                0.3525390625
            ],
            "normalization_schemes": [
                "CTNormalization"
            ],
            "use_mask_for_norm": [
                false
            ],
            "UNet_class_name": "PlainConvUNet",
            "UNet_base_num_features": 32,
            "n_conv_per_stage_encoder": [
                2,
                2,
                2,
                2,
                2,
                2
            ],
            "n_conv_per_stage_decoder": [
                2,
                2,
                2,
                2,
                2
            ],
            "num_pool_per_axis": [
                4,
                5,
                5
            ],
            "pool_op_kernel_sizes": [
                [
                    1,
                    1,
                    1
                ],
                [
                    2,
                    2,
                    2
                ],
                [
                    2,
                    2,
                    2
                ],
                [
                    2,
                    2,
                    2
                ],
                [
                    2,
                    2,
                    2
                ],
                [
                    1,
                    2,
                    2
                ]
            ],
            "conv_kernel_sizes": [
                [
                    3,
                    3,
                    3
                ],
                [
                    3,
                    3,
                    3
                ],
                [
                    3,
                    3,
                    3
                ],
                [
                    3,
                    3,
                    3
                ],
                [
                    3,
                    3,
                    3
                ],
                [
                    3,
                    3,
                    3
                ]
            ],
            "unet_max_num_features": 320,
            "resampling_fn_data": "resample_data_or_seg_to_shape",
            "resampling_fn_seg": "resample_data_or_seg_to_shape",
            "resampling_fn_data_kwargs": {
                "is_seg": false,
                "order": 3,
                "order_z": 0,
                "force_separate_z": null
            },
            "resampling_fn_seg_kwargs": {
                "is_seg": true,
                "order": 1,
                "order_z": 0,
                "force_separate_z": null
            },
            "resampling_fn_probabilities": "resample_data_or_seg_to_shape",
            "resampling_fn_probabilities_kwargs": {
                "is_seg": false,
                "order": 1,
                "order_z": 0,
                "force_separate_z": null
            },
            "batch_dice": false
        }
    },
    "experiment_planner_used": "ExperimentPlanner",
    "label_manager": "LabelManager",
    "foreground_intensity_properties_per_channel": {
        "0": {
            "max": 1965.99072265625,
            "mean": 194.6988067626953,
            "median": 177.3902130126953,
            "min": -248.65533447265625,
            "percentile_00_5": 59.57797622680664,
            "percentile_99_5": 614.022705078125,
            "std": 94.38446044921875
        }
    }
}